llama_index/finetuning/__init__.py
llama_index/finetuning/types.py
llama_index/finetuning/azure_openai/__init__.py
llama_index/finetuning/azure_openai/base.py
llama_index/finetuning/callbacks/__init__.py
llama_index/finetuning/callbacks/finetuning_handler.py
llama_index/finetuning/cross_encoders/__init__.py
llama_index/finetuning/cross_encoders/cross_encoder.py
llama_index/finetuning/cross_encoders/dataset_gen.py
llama_index/finetuning/embeddings/__init__.py
llama_index/finetuning/embeddings/adapter.py
llama_index/finetuning/embeddings/adapter_utils.py
llama_index/finetuning/embeddings/common.py
llama_index/finetuning/embeddings/sentence_transformer.py
llama_index/finetuning/mistralai/__init__.py
llama_index/finetuning/mistralai/base.py
llama_index/finetuning/mistralai/utils.py
llama_index/finetuning/openai/__init__.py
llama_index/finetuning/openai/base.py
llama_index/finetuning/openai/validate_json.py
llama_index/finetuning/rerankers/__init__.py
llama_index/finetuning/rerankers/cohere_reranker.py
llama_index/finetuning/rerankers/dataset_gen.py
llama_index_finetuning-0.4.1.dist-info/METADATA
llama_index_finetuning-0.4.1.dist-info/WHEEL
llama_index_finetuning-0.4.1.dist-info/licenses/LICENSE
llama_index_finetuning-0.4.1.dist-info/RECORD
