Metadata-Version: 2.4
Name: llama-index-finetuning
Version: 0.4.1
Summary: llama-index finetuning
Author-email: Your Name <you@example.com>
License-Expression: MIT
License-File: LICENSE
Requires-Python: <4.0,>=3.10
Requires-Dist: llama-index-core<0.15,>=0.13.0
Requires-Dist: llama-index-embeddings-adapter<0.5,>=0.4.0
Requires-Dist: llama-index-llms-azure-openai<0.5,>=0.4.0
Requires-Dist: llama-index-llms-mistralai<0.8,>=0.7.0
Requires-Dist: llama-index-postprocessor-cohere-rerank<0.6,>=0.5.0
Requires-Dist: mistralai>=1.7.0
Requires-Dist: sentence-transformers>=2.3.0
